{
  "dark": {
    "name": "Catppuccin Frappé Lavender",
    "primary": "#BABBF1",
    "primaryText": "#232634",
    "primaryContainer": "#303446",
    "secondary": "#BABBF1",
    "surface": "#232634",
    "surfaceText": "#C6D0F5",
    "surfaceVariant": "#292C3C",
    "surfaceVariantText": "#A5ADCE",
    "surfaceTint": "#626880",
    "background": "#292C3C",
    "backgroundText": "#C6D0F5",
    "outline": "#51576D",
    "surfaceContainer": "#292C3C",
    "surfaceContainerHigh": "#303446",
    "surfaceContainerHighest": "#414559",
    "error": "#E78284",
    "warning": "#E5C890",
    "info": "#99D1DB",
    "matugen_type": "scheme-neutral"
  },
  "light": {
    "name": "Catppuccin Latte Lavender",
    "primary": "#7287FD",
    "primaryText": "#DCE0E8",
    "primaryContainer": "#EFF1F5",
    "secondary": "#7287FD",
    "surface": "#DCE0E8",
    "surfaceText": "#4C4F69",
    "surfaceVariant": "#E6E9EF",
    "surfaceVariantText": "#6C6F85",
    "surfaceTint": "#ACB0BE",
    "background": "#E6E9EF",
    "backgroundText": "#4C4F69",
    "outline": "#BCC0CC",
    "surfaceContainer": "#E6E9EF",
    "surfaceContainerHigh": "#EFF1F5",
    "surfaceContainerHighest": "#CCD0DA",
    "error": "#D20F39",
    "warning": "#DF8E1D",
    "info": "#04A5E5",
    "matugen_type": "scheme-neutral"
  }
}
